mediascraper/__init__.py
mediascraper/gelbooru.py
mediascraper/hentaihaven.py
mediascraper/pornhub.py
mediascraper/rule34.py
mediascraper-0.0.2.dist-info/METADATA
mediascraper-0.0.2.dist-info/WHEEL
mediascraper-0.0.2.dist-info/top_level.txt
mediascraper-0.0.2.dist-info/RECORD
