Metadata-Version: 2.1
Name: mediascraper
Version: 0.0.2
Summary: A small package for scraping medias.
Home-page: https://github.com/PythonPb/mediascraper
Author: Tim232
Author-email: author@example.com
License: UNKNOWN
Platform: UNKNOWN
Classifier: Programming Language :: Python :: 3
Classifier: License :: OSI Approved :: MIT License
Classifier: Operating System :: OS Independent
